setup.py
rbl_distributions/Binomialdistribution.py
rbl_distributions/Gaussiandistribution.py
rbl_distributions/Generaldistribution.py
rbl_distributions/__init__.py
rbl_distributions.egg-info/PKG-INFO
rbl_distributions.egg-info/SOURCES.txt
rbl_distributions.egg-info/dependency_links.txt
rbl_distributions.egg-info/not-zip-safe
rbl_distributions.egg-info/top_level.txt