Metadata-Version: 1.0
Name: rbl-distributions
Version: 1.1
Summary: Gaussian and Binomial distributions
Home-page: UNKNOWN
Author: Ochieng Billy
Author-email: UNKNOWN
License: UNKNOWN
Platform: UNKNOWN
